gitlabemu/__init__.py
gitlabemu/__main__.py
gitlabemu/ansi.py
gitlabemu/artifacts.py
gitlabemu/chown.py
gitlabemu/configloader.py
gitlabemu/configtool.py
gitlabemu/configtool_ctx.py
gitlabemu/configtool_gitlab.py
gitlabemu/configtool_runner.py
gitlabemu/configtool_vars.py
gitlabemu/configtool_volumes.py
gitlabemu/docker.py
gitlabemu/errors.py
gitlabemu/generator.py
gitlabemu/gitlab_client_api.py
gitlabemu/helpers.py
gitlabemu/jobs.py
gitlabemu/jobtypes.py
gitlabemu/localfiles.py
gitlabemu/localstats.py
gitlabemu/logmsg.py
gitlabemu/pipelines.py
gitlabemu/pstab.py
gitlabemu/references.py
gitlabemu/resnamer.py
gitlabemu/ruleparser.py
gitlabemu/runner.py
gitlabemu/userconfig.py
gitlabemu/userconfigdata.py
gitlabemu/variables.py
gitlabemu/yamlloader.py
gitlabemu/genericci/__init__.py
gitlabemu/genericci/types.py
gitlabemu/gitlab/__init__.py
gitlabemu/gitlab/constraints.py
gitlabemu/gitlab/types.py
gitlabemu/gitlab/urls.py
gitlabemu/glp/__init__.py
gitlabemu/glp/__main__.py
gitlabemu/glp/buildtool.py
gitlabemu/glp/canceltool.py
gitlabemu/glp/dumptool.py
gitlabemu/glp/exporttool.py
gitlabemu/glp/jobstool.py
gitlabemu/glp/listtool.py
gitlabemu/glp/subcommand.py
gitlabemu/glp/subsettool.py
gitlabemu/glp/tool.py
gitlabemu/glp/types.py
gitlabemu/rules/GitlabRuleLexer.py
gitlabemu/rules/GitlabRuleParser.py
gitlabemu/rules/GitlabRuleVisitor.py
gitlabemu/rules/__init__.py
gitlab_emulator-16.3.3.dist-info/METADATA
gitlab_emulator-16.3.3.dist-info/WHEEL
gitlab_emulator-16.3.3.dist-info/entry_points.txt
gitlab_emulator-16.3.3.dist-info/top_level.txt
gitlab_emulator-16.3.3.dist-info/RECORD
