Metadata-Version: 2.1
Name: gitlab-emulator
Version: 16.3.3
Summary: Run/Inspect a .gitlab-ci.yml jobs and pipelines locally
Author: Ian Norton
Author-email: inorton@gmail.com
License: License :: OSI Approved :: MIT License
Requires-Python: >=3.6
Requires-Dist: pyyaml>=5.1
Requires-Dist: requests>=2.25.0
Requires-Dist: requests-toolbelt>=0.9.1
Requires-Dist: certifi>=2022.6
Requires-Dist: antlr4-python3-runtime==4.11.1
Requires-Dist: prompt-toolkit>=3.0
Requires-Dist: python-gitlab==2.10.1; python_version <= "3.6"
Requires-Dist: python-gitlab>=3.2.0; python_version >= "3.7"
Requires-Dist: taskstats==0.0.3; python_version >= "3.7"
